CHANGES.txt
LICENSE.txt
MANIFEST.in
README.txt
setup.py
aDict2.egg-info/PKG-INFO
aDict2.egg-info/SOURCES.txt
aDict2.egg-info/dependency_links.txt
aDict2.egg-info/top_level.txt
adict/__init__.py
adict/_data.py
adict/_strings.py
adict/parser.py
adict/printer.py