Metadata-Version: 1.0
Name: aDict2
Version: 0.1.0
Summary: aDict dictionary format handling
Home-page: http://arseniiv.info/progr/adict
Author: arseniiv
Author-email: arseniiv@gmail.com
License: CC0
Keywords: dictionary text
Platform: UNKNOWN
